leafmaptools/__init__.py
leafmaptools/basemaps.py
leafmaptools/leafmaptools.py
leafmaptools/recorder.py
leafmaptools/styles.py
leafmaptools/tilegrids.py
leafmaptools/utils.py
leafmaptools-0.0.2.dist-info/LICENSE
leafmaptools-0.0.2.dist-info/METADATA
leafmaptools-0.0.2.dist-info/WHEEL
leafmaptools-0.0.2.dist-info/dependency_links.txt
leafmaptools-0.0.2.dist-info/top_level.txt
leafmaptools-0.0.2.dist-info/RECORD
