Metadata-Version: 2.1
Name: leafmaptools
Version: 0.0.2
Summary: A Python package for building a tool widgets infrastructure with ipyleaflet and ipywidgets
Home-page: https://github.com/giswqs/leafmaptools
Author: Qiusheng Wu
Author-email: giswqs@gmail.com
License: MIT license
Keywords: leafmaptools
Platform: UNKNOWN
Classifier: Development Status :: 2 - Pre-Alpha
Classifier: Intended Audience :: Developers
Classifier: License :: OSI Approved :: MIT License
Classifier: Natural Language :: English
Classifier: Programming Language :: Python :: 3
Classifier: Programming Language :: Python :: 3.6
Classifier: Programming Language :: Python :: 3.7
Classifier: Programming Language :: Python :: 3.8
Requires-Python: >=3.5
Requires-Dist: geojson
Requires-Dist: h3
Requires-Dist: ipyfilechooser
Requires-Dist: ipyleaflet
Requires-Dist: ipywidgets
Requires-Dist: mercantile
